datawrangling_lalit/__init__.py
datawrangling_lalit-0.0.1.dist-info/METADATA
datawrangling_lalit-0.0.1.dist-info/WHEEL
datawrangling_lalit-0.0.1.dist-info/top_level.txt
datawrangling_lalit-0.0.1.dist-info/RECORD
