Metadata-Version: 2.1
Name: datawrangling-lalit
Version: 0.0.1
Summary: stats package its very complex
Author: Lalit Sharma (Tata Motors)
Author-email: lalit.sharma1@tatamotors.com
Keywords: python,video,stream,video stream,camera stream,sockets
Classifier: Development Status :: 1 - Planning
Classifier: Intended Audience :: Developers
Classifier: Programming Language :: Python :: 3
Classifier: Operating System :: Unix
Classifier: Operating System :: MacOS :: MacOS X
Classifier: Operating System :: Microsoft :: Windows
Requires-Dist: pandas
